Metadata-Version: 2.1
Name: 88orm
Version: 0.1.9.1
Summary: ORM Service Connector
Home-page: http://pypi.python.org/pypi/88orm/
Author: Rimba Prayoga
Author-email: rimba47prayoga@gmail.com
License: UNKNOWN
Platform: UNKNOWN
Classifier: Programming Language :: Python :: 3
Classifier: License :: OSI Approved :: MIT License
Classifier: Operating System :: OS Independent
Requires-Python: >=3.6
